staview/__init__.py
staview/__main__.py
staview-0.1.2.dist-info/LICENSE
staview-0.1.2.dist-info/METADATA
staview-0.1.2.dist-info/WHEEL
staview-0.1.2.dist-info/entry_points.txt
staview-0.1.2.dist-info/top_level.txt
staview-0.1.2.dist-info/RECORD
