Metadata-Version: 2.1
Name: staview
Version: 0.1.2
Summary: STA report slack visualizer
Author: bunnie
License: MIT
Classifier: Programming Language :: Python :: 3
Requires-Python: >=3.6
License-File: LICENSE
Requires-Dist: npyscreen
